[{"imdb_id": "nm0451307", "name": " Saif Ali Khan"}, {"imdb_id": "nm0007107", "name": " Urmila Matondkar"}, {"imdb_id": "nm0084443", "name": " Seema Biswas"}, {"imdb_id": "nm0820282", "name": " Aditya Srivastava"}, {"imdb_id": "nm0443699", "name": " Pratima Kazmi"}, {"imdb_id": "nm0430799", "name": " Madan Joshi"}, {"imdb_id": "nm1664541", "name": " Zakir Hussain"}, {"imdb_id": "nm1055106", "name": " Abhay Bhargav"}, {"imdb_id": "nm1532568", "name": " Rasika Oak"}, {"imdb_id": "nm1530940", "name": " Seema Adhikari"}, {"imdb_id": "nm3385526", "name": " Gopal K. Singh"}, {"imdb_id": "nm0149441", "name": " Sheeba Chaddha"}, {"imdb_id": "nm1671375", "name": " Rasika Joshi"}, {"imdb_id": "nm2817027", "name": " Kavita Kaushik"}, {"imdb_id": "nm4740190", "name": " Gulfam Khan"}]