[{"imdb_id": "nm0451148", "name": " Aamir Khan"}, {"imdb_id": "nm0534856", "name": " Madhavan"}, {"imdb_id": "nm0430817", "name": " Sharman Joshi"}, {"imdb_id": "nm0004626", "name": " Kareena Kapoor"}, {"imdb_id": "nm1224082", "name": " Boman Irani"}, {"imdb_id": "nm1437925", "name": " Omi Vaidya"}, {"imdb_id": "nm1587175", "name": " Mona Singh"}, {"imdb_id": "nm0412917", "name": " Javed Jaffrey"}, {"imdb_id": "nm0756378", "name": " Parikshat Sahni"}, {"imdb_id": "nm1717985", "name": " Olivier Lafont"}, {"imdb_id": "nm2874992", "name": " Rahul Kumar"}, {"imdb_id": "nm1030306", "name": " Amardeep Jha"}, {"imdb_id": "nm2409254", "name": " Farida Dadi"}, {"imdb_id": "nm1569092", "name": " Mukund Bhatt"}, {"imdb_id": "nm3760619", "name": " Chaitali Bose"}]