[{"imdb_id": "nm0451148", "name": " Aamir Khan"}, {"imdb_id": "nm3087728", "name": " Anushka Sharma"}, {"imdb_id": "nm0795661", "name": " Saurabh Shukla"}, {"imdb_id": "nm0004569", "name": " Sanjay Dutt"}, {"imdb_id": "nm1224082", "name": " Boman Irani"}, {"imdb_id": "nm3818286", "name": " Sushant Singh Rajput"}, {"imdb_id": "nm0756378", "name": " Parikshat Sahni"}, {"imdb_id": "nm1030306", "name": " Amardeep Jha"}, {"imdb_id": "nm4427212", "name": " Reema Debnath"}, {"imdb_id": "nm3358585", "name": " Dheerendra Dwivedi"}, {"imdb_id": "nm2306491", "name": " Sai Gundewar"}, {"imdb_id": "nm1082338", "name": " Ram P. Sethi"}, {"imdb_id": "nm1360697", "name": " Rukhsar Rehman"}, {"imdb_id": "nm0050187", "name": " Arun Bali"}, {"imdb_id": "nm6123790", "name": " Pallavi Batra"}]