[{"imdb_id": "nm0474774", "name": " Akshay Kumar"}, {"imdb_id": "nm0451600", "name": " Anupam Kher"}, {"imdb_id": "nm0048075", "name": " Manoj Bajpayee"}, {"imdb_id": "nm0792116", "name": " Jimmy Sheirgill"}, {"imdb_id": "nm2570245", "name": " Kajal Aggarwal"}, {"imdb_id": "nm0244890", "name": " Divya Dutta"}, {"imdb_id": "nm0434263", "name": " Kishore Kadam"}, {"imdb_id": "nm0788903", "name": " Rajesh Sharma"}, {"imdb_id": "nm1516058", "name": " Deep Raj Rana"}, {"imdb_id": "nm1479650", "name": " Vipin Sharma"}, {"imdb_id": "nm2747851", "name": " Sukhwinder Chahal"}, {"imdb_id": "nm3665336", "name": " Abha Parmar"}, {"imdb_id": "nm1201151", "name": " Mukesh Bhatt"}, {"imdb_id": "nm2717649", "name": " Ujjwal Chopra"}, {"imdb_id": "nm0848308", "name": " Tiku Talsania"}]