[{"imdb_id": "nm1633541", "name": " Ranbir Kapoor"}, {"imdb_id": "nm0712546", "name": " Paresh Rawal"}, {"imdb_id": "nm0463539", "name": " Manisha Koirala"}, {"imdb_id": "nm5817249", "name": " Vicky Kaushal"}, {"imdb_id": "nm1069850", "name": " Dia Mirza"}, {"imdb_id": "nm3087728", "name": " Anushka Sharma"}, {"imdb_id": "nm2128238", "name": " Sonam Kapoor"}, {"imdb_id": "nm6845061", "name": " Jim Sarbh"}, {"imdb_id": "nm1656076", "name": " Karishma Tanna"}, {"imdb_id": "nm1224082", "name": " Boman Irani"}, {"imdb_id": "nm5092725", "name": " Ashnoor Kaur"}, {"imdb_id": "nm3884155", "name": " Siya"}, {"imdb_id": "nm0007102", "name": " Tabu"}, {"imdb_id": "nm0793851", "name": " Sayaji Shinde"}, {"imdb_id": "nm7307982", "name": " Steven Allen Prince"}]