[{"imdb_id": "nm0474774", "name": " Akshay Kumar"}, {"imdb_id": "nm2331000", "name": " Radhika Apte"}, {"imdb_id": "nm2128238", "name": " Sonam Kapoor"}, {"imdb_id": "nm1533122", "name": " Jyoti Subhash"}, {"imdb_id": "nm5043571", "name": " Urmila Mahanta"}, {"imdb_id": "nm1224984", "name": " Suneel Sinha"}, {"imdb_id": "nm2471193", "name": " Sanjay Singh"}, {"imdb_id": "nm7817712", "name": " 'Om' Rakesh Chaturvedi"}, {"imdb_id": "nm4668497", "name": " Mrinmayee Godbole"}, {"imdb_id": "nm10056482", "name": " Mridul Satam"}, {"imdb_id": "nm5110857", "name": " Parul Chauhan"}, {"imdb_id": "nm3198740", "name": " Saurabh Agarwal"}, {"imdb_id": "nm0000821", "name": " Amitabh Bachchan"}, {"imdb_id": "nm9190300", "name": " Varun Bag"}, {"imdb_id": "nm8479608", "name": " Himika Bose"}]